docal_tkinter/__init__.py
docal_tkinter/__main__.py
docal_tkinter/app.py
docal_tkinter/menubar.py
docal_tkinter/sidebar.py
docal_tkinter/toolbar.py
docal_tkinter/worksheet.py
docal_tkinter-3.0.5.dist-info/LICENSE
docal_tkinter-3.0.5.dist-info/METADATA
docal_tkinter-3.0.5.dist-info/WHEEL
docal_tkinter-3.0.5.dist-info/top_level.txt
docal_tkinter-3.0.5.dist-info/RECORD
